upset/__init__.py
upset-0.0.1.dist-info/LICENSE
upset-0.0.1.dist-info/METADATA
upset-0.0.1.dist-info/WHEEL
upset-0.0.1.dist-info/RECORD
