Metadata-Version: 2.1
Name: upset
Version: 0.0.1
Summary: ʌpˈset - application's settings
Home-page: https://github.com/llybin/upset
License: BSD-3-Clause
Author: Lev Lybin
Author-email: lev.lybin@gmail.com
Requires-Python: >=3.10
Classifier: License :: OSI Approved :: BSD License
Classifier: Programming Language :: Python :: 3
Classifier: Programming Language :: Python :: 3.10
Classifier: Programming Language :: Python :: 3.11
Classifier: Programming Language :: Python :: 3.12
Classifier: Programming Language :: Python :: 3.13
Project-URL: Repository, https://github.com/llybin/upset
